license
setup.cfg
setup.py
twpl/__init__.py
twpl/twpl.py
twpl.egg-info/PKG-INFO
twpl.egg-info/SOURCES.txt
twpl.egg-info/dependency_links.txt
twpl.egg-info/requires.txt
twpl.egg-info/top_level.txt
twpl.egg-info/zip-safe